dataprep/VERSION
dataprep/__init__.py
dataprep/__main__.py
dataprep/config.py
dataprep/dirutils.py
dataprep/fileutils.py
dataprep/logging.yaml
dataprep/noneng.py
dataprep/prepconfig.py
dataprep/stemming.py
dataprep/subtokens.py
dataprep/util.py
dataprep/api/__init__.py
dataprep/api/common.py
dataprep/api/corpus.py
dataprep/api/text.py
dataprep/bpepkg/__init__.py
dataprep/bpepkg/bpe_config.py
dataprep/bpepkg/bpe_encode.py
dataprep/bpepkg/bpe_learn.py
dataprep/bpepkg/cache.py
dataprep/bpepkg/merge.py
dataprep/bpepkg/wild_bpe.py
dataprep/cli/__init__.py
dataprep/cli/impl.py
dataprep/cli/spec.py
dataprep/cli/vocab.py
dataprep/data/bpe/10k/merges.txt
dataprep/data/bpe/case/0/merges.txt
dataprep/data/bpe/case/10k/merges.txt
dataprep/data/bpe/case/1k/merges.txt
dataprep/data/bpe/case/5k/merges.txt
dataprep/data/bpe/nocase/0/merges.txt
dataprep/parse/__init__.py
dataprep/parse/core.py
dataprep/parse/matchers.py
dataprep/parse/subtokens.py
dataprep/pipeline/__init__.py
dataprep/pipeline/bpelearner.py
dataprep/pipeline/bperegistry.py
dataprep/pipeline/dataset.py
dataprep/pipeline/parse_projects.py
dataprep/pipeline/stages.py
dataprep/pipeline/to_repr.py
dataprep/pipeline/vocab.py
dataprep/pipeline/vocabloader.py
dataprep/preprocess/__init__.py
dataprep/preprocess/core.py
dataprep/preprocess/metadata.py
dataprep/preprocess/placeholders.py
dataprep/preprocess/reprconfig.py
dataprep/tokens/__init__.py
dataprep/tokens/containers.py
dataprep/tokens/noneng.py
dataprep/tokens/numeric.py
dataprep/tokens/rootclasses.py
dataprep/tokens/whitespace.py
dataprep/tokens/word.py
tests/__init__.py
tests/test_corpus_b2b.py
tests/test_subword_separation.py
tests/test_to_repr.py
tests/api/__init__.py
tests/api/test_corpus.py
tests/bpepkg/__init__.py
tests/bpepkg/test_merge.py
tests/bpepkg/wild_bpe_performance.py
tests/cli/__init__.py
tests/cli/test_spec.py
tests/infrastructure/__init__.py
tests/infrastructure/test_bpelearner.py
tests/infrastructure/test_bperegistry.py
giganticode_dataprep-1.0.0a12.dist-info/LICENSE
giganticode_dataprep-1.0.0a12.dist-info/METADATA
giganticode_dataprep-1.0.0a12.dist-info/WHEEL
giganticode_dataprep-1.0.0a12.dist-info/entry_points.txt
giganticode_dataprep-1.0.0a12.dist-info/top_level.txt
giganticode_dataprep-1.0.0a12.dist-info/RECORD
